src/ProyectoHa/__init__.py
src/ProyectoHa/example.py
prha-0.0.1.dist-info/METADATA
prha-0.0.1.dist-info/WHEEL
prha-0.0.1.dist-info/RECORD
